{
    "Student Number": "150120029",
    "Student Name": "Kardelen T\u00fcrkay",
    "Year": 2,
    "Advisor": {
        "Name": "Fatma Corut Ergin",
        "Department": "CSE",
        "Rank": "Dr.\u00c3\u2013\u00c4\u0178r.\u00c3\u0153yesi"
    },
    "Transcript Before": {
        "Course List": [
            [
                {
                    "Course Name": "Atat\u00c3\u00bcrk \u00c4\u00b0lkeleri ve \u00c4\u00b0nk\u00c4\u00b1lap Tarihi I",
                    "Course Credit": 2,
                    "Semester": 1,
                    "Prerequisite": null
                },
                "FF"
            ],
            [
                {
                    "Course Name": "Introduction to Modern Biology",
                    "Course Credit": 5,
                    "Semester": 1,
                    "Prerequisite": null
                },
                "DC"
            ],
            [
                {
                    "Course Name": "Introduction to Computer Engineering",
                    "Course Credit": 4,
                    "Semester": 1,
                    "Prerequisite": null
                },
                "AA"
            ],
            [
                {
                    "Course Name": "Computer Programming I",
                    "Course Credit": 6,
                    "Semester": 1,
                    "Prerequisite": null
                },
                "BB"
            ],
            [
                {
                    "Course Name": "Calculus I",
                    "Course Credit": 6,
                    "Semester": 1,
                    "Prerequisite": null
                },
                "CB"
            ],
            [
                {
                    "Course Name": "Physics I",
                    "Course Credit": 4,
                    "Semester": 1,
                    "Prerequisite": null
                },
                "BA"
            ],
            [
                {
                    "Course Name": "Physics Lab I",
                    "Course Credit": 2,
                    "Semester": 1,
                    "Prerequisite": null
                },
                "BB"
            ],
            [
                {
                    "Course Name": "T\u00c3\u00bcrk Dili I",
                    "Course Credit": 2,
                    "Semester": 1,
                    "Prerequisite": null
                },
                "BA"
            ],
            [
                {
                    "Course Name": "Atat\u00c3\u00bcrk \u00c4\u00b0lkeleri ve \u00c4\u00b0nk\u00c4\u00b1lap Tarihi II",
                    "Course Credit": 2,
                    "Semester": 2,
                    "Prerequisite": null
                },
                "FF"
            ],
            [
                {
                    "Course Name": "Computer Programming II",
                    "Course Credit": 6,
                    "Semester": 2,
                    "Prerequisite": null
                },
                "CC"
            ],
            [
                {
                    "Course Name": "Calculus II",
                    "Course Credit": 6,
                    "Semester": 2,
                    "Prerequisite": null
                },
                "BA"
            ],
            [
                {
                    "Course Name": "Linear Algebra for Computer Engineering",
                    "Course Credit": 5,
                    "Semester": 2,
                    "Prerequisite": null
                },
                "FF"
            ],
            [
                {
                    "Course Name": "Physics II",
                    "Course Credit": 4,
                    "Semester": 2,
                    "Prerequisite": null
                },
                "BB"
            ],
            [
                {
                    "Course Name": "Physics Lab II",
                    "Course Credit": 2,
                    "Semester": 2,
                    "Prerequisite": null
                },
                "DD"
            ],
            [
                {
                    "Course Name": "T\u00c3\u00bcrk Dili II",
                    "Course Credit": 2,
                    "Semester": 2,
                    "Prerequisite": null
                },
                "AA"
            ],
            [
                {
                    "Course Name": "Self Management",
                    "Course Credit": 3,
                    "Quota": 20,
                    "Prerequisite": null,
                    "Elective Type": "NTE"
                },
                "CB"
            ],
            [
                {
                    "Course Name": "Discrete Computational Structures",
                    "Course Credit": 6,
                    "Semester": 3,
                    "Prerequisite": null
                },
                "BB"
            ],
            [
                {
                    "Course Name": "Data Structures",
                    "Course Credit": 7,
                    "Semester": 3,
                    "Prerequisite": "Computer Programming II"
                },
                "DD"
            ],
            [
                {
                    "Course Name": "Engineering Economy",
                    "Course Credit": 4,
                    "Semester": 3,
                    "Prerequisite": null
                },
                "DD"
            ],
            [
                {
                    "Course Name": "Electric Circuits",
                    "Course Credit": 5,
                    "Semester": 3,
                    "Prerequisite": null
                },
                "BA"
            ],
            [
                {
                    "Course Name": "Differential Equations",
                    "Course Credit": 4,
                    "Semester": 3,
                    "Prerequisite": null
                },
                "AA"
            ],
            [
                {
                    "Course Name": "Numerical Methods",
                    "Course Credit": 4,
                    "Semester": 3,
                    "Prerequisite": null
                },
                "FD"
            ]
        ],
        "Attended Credit": 91,
        "Completed Credit": 78,
        "Point": 210.5,
        "GANO": 2.31
    },
    "Course Offered": [
        {
            "Course Name": "Analysis of Algorithms",
            "Course Credit": 6,
            "Semester": 4,
            "Prerequisite": "Data Structures"
        },
        {
            "Course Name": "Systems Programming",
            "Course Credit": 7,
            "Semester": 4,
            "Prerequisite": null
        },
        {
            "Course Name": "Principles of Programming Languages",
            "Course Credit": 4,
            "Semester": 4,
            "Prerequisite": null
        },
        {
            "Course Name": "Electronics",
            "Course Credit": 5,
            "Semester": 4,
            "Prerequisite": null
        },
        {
            "Course Name": "Introduction to Probability and Statistics",
            "Course Credit": 5,
            "Semester": 4,
            "Prerequisite": null
        }
    ],
    "Errors": []
}